{
  "slug": "add-roles-permissions",
  "display_title": "Customize Write Access",
  "pitch": "Decide who can change what in your team's brain. Lock specific areas (brand strategy, pricing, the saved instructions that shape how Runneth behaves) to specific people. Runneth blocks unauthorized edits, routes change requests through your approval channel, and stamps every save so you always see who wrote what.",
  "status": "proven",
  "category": "agent-foundations",
  "github_path": "add-roles-permissions"
}
