{
  "version": 1,
  "slugs": [
    "authenticate-apps",
    "bootcamp",
    "plan-mode",
    "share-use-case",
    "routine-storage-audit",
    "self-iteration-loop",
    "team-member-memory",
    "review-library",
    "competitor-intel",
    "static-ad-gen",
    "brand-kit",
    "landing-page-experiments",
    "landing-page-summary",
    "optimize-landing-page",
    "building-integrations",
    "integration-capabilities-library",
    "add-roles-permissions",
    "import-from-ai",
    "performance-bundle",
    "brand-audit",
    "paid-strategy-audit",
    "creative-deep-dive",
    "weekly-performance-deck"
  ],
  "excluded": [
    {
      "slug": "ugc-creator-programme",
      "reason": "Source is a zip in the repo; not directly browseable. Restore in v2."
    },
    {
      "slug": "corpus-search",
      "reason": "App uses a SQLite backend; not a filesystem+HTML use case for the public library."
    },
    {
      "slug": "file-explorer",
      "reason": "App uses a SQLite backend; not a filesystem+HTML use case for the public library."
    },
    {
      "slug": "conversation-manager",
      "reason": "App reads the runtime conversations SQLite DB; not a filesystem+HTML use case for the public library."
    },
    {
      "slug": "brief-qa",
      "reason": "App uses a SQLite backend for rubric/score history; not a filesystem+HTML use case for the public library."
    },
    {
      "slug": "creative-qa",
      "reason": "App uses a SQLite backend; not a filesystem+HTML use case for the public library."
    },
    {
      "slug": "video-asset-search",
      "reason": "App uses a SQLite shots/clips DB written by a Python pipeline; not a filesystem+HTML use case for the public library."
    },
    {
      "slug": "video-qa",
      "reason": "App uses a SQLite backend; not a filesystem+HTML use case for the public library."
    },
    {
      "slug": "meta-connect-use-case",
      "reason": "Stateful OAuth app with a server backend (token + secret stored on disk); not a filesystem+HTML use case for the public library."
    },
    {
      "slug": "csm-alerts",
      "reason": "No folder exists in the repo for this slug; site silently drops it. Hide until restored."
    },
    {
      "slug": "deploy-security-protocol",
      "reason": "Renamed to add-roles-permissions."
    },
    {
      "slug": "add-permissions",
      "reason": "Renamed to add-roles-permissions."
    }
  ]
}
